cufjc/__init__.py
cufjc/core.py
cufjc-1.6.0.dist-info/LICENSE
cufjc-1.6.0.dist-info/METADATA
cufjc-1.6.0.dist-info/WHEEL
cufjc-1.6.0.dist-info/top_level.txt
cufjc-1.6.0.dist-info/RECORD
