Metadata-Version: 2.1
Name: cufjc
Version: 1.6.0
Summary: The Python package for the composite uFJC (cuFJC) model.
Home-page: https://github.com/jasonmulderrig/cuFJC
Author: Jason Mulderrig, Brandon Talamini, Nikolaos Bouklas
Author-email: jpm445@cornell.edu, talamini1@llnl.gov, nb589@cornell.edu
Maintainer: Jason Mulderrig
Maintainer-email: jpm445@cornell.edu, mulderrig.jason@gmail.com
License: GNU General Public License v3 or later (GPLv3+)
Keywords: ufjc,cufjc,asymptotic matching,thermodynamics,statistical mechanics,chain extensibility
Classifier: Development Status :: 3 - Alpha
Classifier: Intended Audience :: Science/Research
Classifier: License :: OSI Approved :: GNU General Public License v3 or later (GPLv3+)
Classifier: Natural Language :: English
Classifier: Operating System :: Unix
Classifier: Programming Language :: Python :: 3.5
Classifier: Programming Language :: Python :: 3.6
Classifier: Programming Language :: Python :: 3.7
Classifier: Programming Language :: Python :: 3.8
Classifier: Programming Language :: Python :: 3.9
Classifier: Programming Language :: Python :: 3.10
Classifier: Topic :: Scientific/Engineering
Requires-Python: <4,>=3.5
License-File: LICENSE
Requires-Dist: numpy
